<?xml version="1.0" encoding="UTF-8"?>

<dict num="219" id="219" name="219">

<key>adapt</key>

<ps>ə'dæpt</ps>

<pron>http://res.iciba.com/resource/amp3/oxford/0/dc/63/dc63e9b5379cfe743998947870c892d6.mp3</pron>

<ps>əˈdæpt</ps>

<pron>http://res.iciba.com/resource/amp3/1/0/0b/85/0b859acdc7747ee0509ffc1024158987.mp3</pron>

<pos>vi.</pos>

<acceptation>适应于，适应不同情况（或环境）(to)；

</acceptation>

<pos>vt.</pos>

<acceptation>改编，改写；改变…以适合(for)；

</acceptation>

<sent><orig>

Allow yourself to adapt to the environment, because you never adapt to the environment.

</orig>

<trans>

让自己去适应环境，因为环境永远不会来适应你。

</trans></sent>

<sent><orig>

I find it hardto adapt myself to my new school.

</orig>

<trans>

我发现我很难适应新的学校。

</trans></sent>

<sent><orig>

The program provides job training for people who otherwise could not adapt attend college.

</orig>

<trans>

这项计划为那些不能上大学的人提供工作培训。

</trans></sent>

<sent><orig>

Lacking in awareness, animals have to passively adapt themselves to the living environments.

</orig>

<trans>

动物没有觉性，只能被动地适应生存环境。

</trans></sent>

<sent><orig>

Ordinary pre-school education institutions should be able to adapt their lives to receive the disabled child.

</orig>

<trans>

普通幼儿教育机构应当接收能适应其生活的残疾幼儿。

</trans></sent>

</dict>
