<?xml version="1.0" encoding="UTF-8"?>

<dict num="219" id="219" name="219">

<key>afterwards</key>

<ps>'ɑ:ftəwədz</ps>

<pron>http://res.iciba.com/resource/amp3/0/0/62/2f/622f90ceba19c667b7d2620169144476.mp3</pron>

<ps>'æftərwərdz</ps>

<pron>http://res.iciba.com/resource/amp3/1/0/62/2f/622f90ceba19c667b7d2620169144476.mp3</pron>

<pos>adv.</pos>

<acceptation>然后，后来地；以后；之后；继；

</acceptation>

<sent><orig>

I wrote that (long) afterwards.

</orig>

<trans>

后来（或很久以后）我才写了那些东西。

</trans></sent>

<sent><orig>

About an hour afterwards he slept in the Lord.

</orig>

<trans>

一小时后，他已长眠于天国。

</trans></sent>

<sent><orig>

Afterwards he went abroad.

</orig>

<trans>

之后他到国外去了。

</trans></sent>

<sent><orig>

We plan to have a luncheon to celebrate this event, and take a group picture afterwards.

</orig>

<trans>

我们计划举行特别午餐来庆祝，之后再拍团体照留念。

</trans></sent>

<sent><orig>

Shortly afterwards they went below.

</orig>

<trans>

等一会，两人下去。

</trans></sent>

</dict>
