<?xml version="1.0" encoding="UTF-8"?>

<dict num="219" id="219" name="219">

<key>brown</key>

<ps>braʊn</ps>

<pron>http://res.iciba.com/resource/amp3/oxford/0/ed/f9/edf9ec61ec5eb07a951a287e52eedf17.mp3</pron>

<ps>braʊn</ps>

<pron>http://res.iciba.com/resource/amp3/1/0/6f/f4/6ff47afa5dc7daa42cc705a03fca8a9b.mp3</pron>

<pos>adj.</pos>

<acceptation>褐色的；黑暗的；（纸、棉布或麻布等）本色的；（皮毛、发、羽）呈褐色的；

</acceptation>

<pos>n.</pos>

<acceptation>深色；褐色（或棕色）颜料（或染料）；褐色（或棕色）的衣服（或织物）；棕色皮肤的（亚洲）人（尤指印度人或巴基斯坦人）；

</acceptation>

<pos>vt.&amp; vi.</pos>

<acceptation>（使）呈（或变成）褐色（或棕色）（尤指日晒或经烘烤）；炸（或烤）成褐色；

</acceptation>

<sent><orig>

You have a call from Mr. Brown.There was a call from Mr. Brown.Mr. Brown called you.

</orig>

<trans>

刚才有个Brown先生打电话找你。

</trans></sent>

<sent><orig>

No. What do you have in brown suede jackets size BROWN?

</orig>

<trans>

没有。你们这有棕色的夹克吗？BROWN号的。

</trans></sent>

<sent><orig>

Hello, housekeeping. Is it Mr.Brown?

</orig>

<trans>

喂，这里是客房部，您是Brown先生吗？

</trans></sent>

<sent><orig>

In Brown's case, living without insurance is a deliberate gamble.

</orig>

<trans>

在Brown的例子中，放弃保险是一项故意为之的赌博。

</trans></sent>

<sent><orig>

Nickelodeon says despite hundreds of protest calls, Brown was nominated by kids several months ago.

</orig>

<trans>

Nickelodeon称排除数百人的反对呼声，Brown曾在几个月前被儿童提名。

</trans></sent>

</dict>
