<?xml version="1.0" encoding="UTF-8"?>

<dict num="219" id="219" name="219">

<key>common</key>

<ps>'kɒmən</ps>

<pron>http://res.iciba.com/resource/amp3/0/0/9e/fa/9efab2399c7c560b34de477b9aa0a465.mp3</pron>

<ps>ˈkɑmən</ps>

<pron>http://res.iciba.com/resource/amp3/1/0/9e/fa/9efab2399c7c560b34de477b9aa0a465.mp3</pron>

<pos>adj.</pos>

<acceptation>普通的；通俗的；[数学]公共的；共有的；

</acceptation>

<pos>n.</pos>

<acceptation>[法律]（对土地、水域的）共有权；公共用地；普通；平民；

</acceptation>

<sent><orig>

This paper describes how to realize COMMON-ISDN-API (CAPI) and the layered driver for ISDN Terminal Adapter.

</orig>

<trans>

本文对通用ISDN（综合业务数字网）应用程序接口规范(CAPI:COMMON-ISDN-API)以及ISDNTA(Terminal Adapter)分层驱动程序进行了研究开发。

</trans></sent>

<sent><orig>

Therefore use common words and common meanings. Write for the common man and the common woman.

</orig>

<trans>

因此，要使用普通的词语表达普通的意思，为普通人撰写合同。

</trans></sent>

<sent><orig>

Common sense is not sense common to everyone, but sense in common things.

</orig>

<trans>

常识不是人人都有的知识，而是关于常见事物的知识。

</trans></sent>

<sent><orig>

Common sense, common care, common prudence, were all sunk in Mrs. Dashwood's romantic delicacy.

</orig>

<trans>

一般人常有的理智、关心和谨慎统统渗入到达什伍德太太的浪漫、柔弱的思想中去了。

</trans></sent>

<sent><orig>

My life was the common kind, with common desires and fears.

</orig>

<trans>

我的一生曾经与市井无异，有同一样的欲望和恐惧。

</trans></sent>

</dict>
