<?xml version="1.0" encoding="UTF-8"?>

<dict num="219" id="219" name="219">

<key>hardly</key>

<ps>ˈhɑ:dli</ps>

<pron>http://res.iciba.com/resource/amp3/oxford/0/0e/e5/0ee5d8ffd792635eaf4c8826fe943fcb.mp3</pron>

<ps>ˈhɑrdli</ps>

<pron>http://res.iciba.com/resource/amp3/1/0/53/f7/53f7e75406d3b00807bb22716d489a23.mp3</pron>

<pos>adv.</pos>

<acceptation>几乎不；简直不；刚刚；严厉地，粗鲁地；

</acceptation>

<sent><orig>

The animal hardly makes any movement, hardly use any energy, and hardly needs rood.

</orig>

<trans>

动物几乎没有作任何运动，几乎不用能量也几乎不需要。

</trans></sent>

<sent><orig>

The animal hardly makes any movement, hardly use any energy, and hardly needs any rood.

</orig>

<trans>

动物几乎没有作出任何运动，几乎使用任何能源，几乎不需要任何口。

</trans></sent>

<sent><orig>

We had hardly begun/Hardly had we begun our walk when it began to rain.

</orig>

<trans>

我们刚一举步就下起雨来了。

</trans></sent>

<sent><orig>

Men are also much less hesitant about having sex with someone they hardly know.

</orig>

<trans>

男人在与他们压根儿不认识的人发生性关系时也绝少会犹疑。

</trans></sent>

<sent><orig>

I could hardly keep anything down for about three days.

</orig>

<trans>

3天来我吃了东西就吐出来。

</trans></sent>

</dict>
