<?xml version="1.0" encoding="UTF-8"?>

<dict num="219" id="219" name="219">

<key>highly</key>

<ps>ˈhaɪli</ps>

<pron>http://res.iciba.com/resource/amp3/oxford/0/66/e8/66e8539a2edb4a565b3ffb19f72d03bf.mp3</pron>

<ps>'haɪlɪ</ps>

<pron>http://res.iciba.com/resource/amp3/1/0/24/62/2462ff5717c1677039c79e415fb8d9da.mp3</pron>

<pos>adv.</pos>

<acceptation>高度地；极，非常；非常赞许地；

</acceptation>

<sent><orig>

Aerostatic bearing has highly rotating precision and widely applies to the highly precision processing equipment.

</orig>

<trans>

空气轴承以其回转精度高而广泛地应用于高精密加工设备。

</trans></sent>

<sent><orig>

Stress seems to be caused by highly technical, highly rushed modern way of life.

</orig>

<trans>

看起来压力是由高科技，高节奏的现代生活方式所引起的。

</trans></sent>

<sent><orig>

Effectively managing a ventilator today is a highly-specialized procedure requiring art, science, and highly specialized tools.

</orig>

<trans>

今天有效地管理一套通风设备是需要艺术，科学的一个高度专业化的程式，并且高度专业化工具。

</trans></sent>

<sent><orig>

So the highly valued power has impeded the course of highly praised law.

</orig>

<trans>

固有的“贵势”传统阻碍了“尚法”的进程。

</trans></sent>

<sent><orig>

Do you treat the highly likely as certain and the highly unlikely as impossible?

</orig>

<trans>

你是否把“可能性高”看作“确实”，把“可能性低”看作“不可能”？

</trans></sent>

</dict>
