<?xml version="1.0" encoding="UTF-8"?>

<dict num="219" id="219" name="219">

<key>promise</key>

<ps>'prɒmɪs</ps>

<pron>http://res.iciba.com/resource/amp3/oxford/0/98/d7/98d7159906eeb60e80f8ab237d10964c.mp3</pron>

<ps>ˈprɑmɪs</ps>

<pron>http://res.iciba.com/resource/amp3/1/0/b3/21/b321de3bdc299ec807e9f795d7d9deeb.mp3</pron>

<pos>vt.</pos>

<acceptation>允诺，许诺；给人以…的指望或希望；

</acceptation>

<pos>vi.</pos>

<acceptation>许诺；有指望，有前途；

</acceptation>

<pos>n.</pos>

<acceptation>许诺；希望，指望；允诺的东西；

</acceptation>

<sent><orig>

A promise is a promise.(made a promise and keep a promise).

</orig>

<trans>

信守承诺。阿甘信守了承诺，最后也得到了最好的回报。

</trans></sent>

<sent><orig>

Miguel: I promise. And I promise you a nice present for Christmas, too.

</orig>

<trans>

米盖尔：我答应你。我还要送给你一个漂亮的圣诞节礼物呢。

</trans></sent>

<sent><orig>

Never make promise to anyone and never trust the promise that anyone makes to you.

</orig>

<trans>

不针对任何人任何事做出任何承诺，并永不相信任何人对你所做出的承诺。

</trans></sent>

<sent><orig>

This time, she promise the promise, can't again abdication second time.

</orig>

<trans>

这次，她许下诺言，不会再放弃第二次。

</trans></sent>

<sent><orig>

Almasy: &quot;I promise, I'll back for you. I promise, I'll never leave you. &quot;

</orig>

<trans>

埃尔麦西：“我答应你，我一定回来找你，我包管，我将永不脱离你。”

</trans></sent>

</dict>
