<?xml version="1.0" encoding="UTF-8"?>

<dict num="219" id="219" name="219">

<key>punishment</key>

<ps>ˈpʌnɪʃmənt</ps>

<pron>http://res.iciba.com/resource/amp3/oxford/0/07/32/0732365014720f5b7aba5cb53e669574.mp3</pron>

<ps>ˈpʌnɪʃmənt</ps>

<pron>http://res.iciba.com/resource/amp3/1/0/97/d8/97d839ea4c0f5d558e15e007ec8852e7.mp3</pron>

<pos>n.</pos>

<acceptation>刑罚，惩罚；严厉对待；&lt;口&gt;给吃苦头；

</acceptation>

<sent><orig>

The parole originating from capitalistic punishment system is an important way of enforcement of punishment.

</orig>

<trans>

假释制度是近代资产阶级刑罚制度的产物，是一项重要的行刑制度。

</trans></sent>

<sent><orig>

He is under security punishment or disciplinary punishment that has not been executed or finished yet.

</orig>

<trans>

二受保安处分或感训处分之裁判确定，尚未执行或执行未毕者。

</trans></sent>

<sent><orig>

The tendency of mitigation of punishment is the world trend of punishment now.

</orig>

<trans>

刑罚趋轻和轻刑化是世界刑罚发展的趋势。

</trans></sent>

<sent><orig>

Criminal elements who voluntarily surrender may be given a lesser punishment or a mitigated punishment.

</orig>

<trans>

对于自首的犯罪分子，可以从轻或者减轻处罚。

</trans></sent>

<sent><orig>

An accomplice shall be given a lighter or mitigated punishment or be exempted from punishment.

</orig>

<trans>

对于从犯，应当从轻、减轻处罚或者免除处罚。

</trans></sent>

</dict>
