<?xml version="1.0" encoding="UTF-8"?>

<dict num="219" id="219" name="219">

<key>reasonable</key>

<ps>ˈri:znəbl</ps>

<pron>http://res.iciba.com/resource/amp3/oxford/0/f3/60/f360dbf19ed15d5ded074250943bd59a.mp3</pron>

<ps>ˈrizənəbəl</ps>

<pron>http://res.iciba.com/resource/amp3/1/0/05/ae/05aef0a108ec7ab0bba2d595c91e8106.mp3</pron>

<pos>adj.</pos>

<acceptation>合理的，公道的；明白道理的；适当的；有理性的；

</acceptation>

<sent><orig>

A reasonable man is reasonable. A rational man is never reasonable.

</orig>

<trans>

一个合理的人是合理的，一个理性的人是从来都不合理的。

</trans></sent>

<sent><orig>

Determination reasonable transmission route, through computation parts and so on choice reasonable electrical machinery, speed reducer.

</orig>

<trans>

确定合理的传动路线，通过计算选择合理的电机、减速机等部件。

</trans></sent>

<sent><orig>

She said the United States knows are reasonable reasonable security concerns about the service, but.

</orig>

<trans>

她说，美国了解在黑莓服务方面存在合理的安全性担忧。

</trans></sent>

<sent><orig>

I want to argue that it is reasonable to believe in God.

</orig>

<trans>

我坚持认为，信仰上帝是合情合理的。

</trans></sent>

<sent><orig>

Products in the grocery are sold at reasonable price.

</orig>

<trans>

这间杂货店的产品价格公道。

</trans></sent>

</dict>
