<?xml version="1.0" encoding="UTF-8"?>

<dict num="219" id="219" name="219">

<key>team</key>

<ps>ti:m</ps>

<pron>http://res.iciba.com/resource/amp3/oxford/0/9e/7a/9e7a75ea37fea8a983afca5eee568ccc.mp3</pron>

<ps>tim</ps>

<pron>http://res.iciba.com/resource/amp3/1/0/f8/94/f894427cc1c571f79da49605ef8b112f.mp3</pron>

<pos>n.</pos>

<acceptation>队，组；团队；工作组；（野鸭等）群，同胎仔；

</acceptation>

<pos>vi.</pos>

<acceptation>协同工作；合作；把（牛马等）联套在车上；

</acceptation>

<sent><orig>

The first game team defeated the team, defending champion team has defeated Team Hubei.

</orig>

<trans>

揭幕战山西队战胜吉林队，卫冕冠军广东队战胜了湖北队。

</trans></sent>

<sent><orig>

Reporting team, Treasury Team, Credit Team, Legal Department, WD Department A, Operation Department.

</orig>

<trans>

报表组，资金组，信贷部，法律部，人力资源部，A部门，相关业务部门。

</trans></sent>

<sent><orig>

Reporting team, Treasury Team, Credit Team, Department, WD Department, G&amp;A, Operation Department.

</orig>

<trans>

报表组，资金组，信贷部，法律部，人力资源部，G&amp;A部门，相关业务部门。

</trans></sent>

<sent><orig>

Each team may enter one team leader, one coach and one team doctor.

</orig>

<trans>

（一）参赛单位可报领队1人、教练1人、医生1人。

</trans></sent>

<sent><orig>

After defeating team, the Italian team will contest for the Worldchampion with team.

</orig>

<trans>

击败德国队后，意大利队将和法国队争夺冠军。

</trans></sent>

</dict>
