<?xml version="1.0" encoding="UTF-8"?>

<dict num="219" id="219" name="219">

<key>theory</key>

<ps>ˈθiəri</ps>

<pron>http://res.iciba.com/resource/amp3/0/0/af/54/af5443b3a2c16990166ab234f3bfb569.mp3</pron>

<ps>ˈθiəri, ˈθɪri</ps>

<pron>http://res.iciba.com/resource/amp3/1/0/af/54/af5443b3a2c16990166ab234f3bfb569.mp3</pron>

<pos>n.</pos>

<acceptation>学说；理论；原理；推测；

</acceptation>

<sent><orig>

The understanding of electromagnetic radiation underwent particle theory, wave theory, wave-particle theory.

</orig>

<trans>

电磁辐射的认识经历了微粒说、波动说、波粒二象性的过程。

</trans></sent>

<sent><orig>

I divide the forensic accounting theory system into the basic theory and the application theory.

</orig>

<trans>

本文将法务会计理论体系划分为基础理论和应用理论两个层次。

</trans></sent>

<sent><orig>

Research and teaching: microeconomic theory, game theory and social choice theory.

</orig>

<trans>

主要研究和教学领域：微观经济理论、对策论、社会选择理论。

</trans></sent>

<sent><orig>

This paper of compensation management such as fairness theory, double factor theory and expectation theory.

</orig>

<trans>

公平理论、双因素理论、期望理论等激励理论也要经常应用。

</trans></sent>

<sent><orig>

The strength theory,dendritic bridging theory,solidification shrinkage reparing theory and CSC criterion,HCS criterion are stressed.

</orig>

<trans>

重点介绍了强度理论、晶间搭桥理论、凝固收缩补偿理论和 CSC判据、HCS判据。

</trans></sent>

</dict>
