<?xml version="1.0" encoding="UTF-8"?>

<dict num="219" id="219" name="219">

<key>therefore</key>

<ps>ˈðeəfɔ:(r)</ps>

<pron>http://res.iciba.com/resource/amp3/oxford/0/dd/d5/ddd59fe3869c67ec4b1cc9b9a5a9b0cf.mp3</pron>

<ps>ˈðɛrˌfɔr, -ˌfor</ps>

<pron>http://res.iciba.com/resource/amp3/1/0/c4/ad/c4ad57a2c37893918ba243790304c2f0.mp3</pron>

<pos>adv.</pos>

<acceptation>因此；所以；故；乃；

</acceptation>

<sent><orig>

Is not for any repayment, therefore the concern, will not be for any tomorrow therefore anticipation.

</orig>

<trans>

不是为了什么回报所以关怀，不是为了什么明天所以期待。

</trans></sent>

<sent><orig>

She's beautiful and therefore to be woo'd She is a woman, therefore to be won.

</orig>

<trans>

因为她生的美丽，所以被男人追求；因为她是女人，所以被男人俘获。

</trans></sent>

<sent><orig>

God says to man,&quot;I heal you therefore I hurt, love you therefore punish.&quot;

</orig>

<trans>

神对人说：“我医治你所以伤害你，爱你所以惩罚你。”

</trans></sent>

<sent><orig>

Therefore, we had the first distinct experience to the white Algeria.

</orig>

<trans>

因此，我对白色的阿尔及利亚有了第一次真切的休会。

</trans></sent>

<sent><orig>

Therefore the generators drive the synthesis, more or less.

</orig>

<trans>

因此发生器水晶推动合成，更大或更小。

</trans></sent>

</dict>
